viable/__init__.py
viable-0.0.2.dist-info/LICENSE
viable-0.0.2.dist-info/METADATA
viable-0.0.2.dist-info/WHEEL
viable-0.0.2.dist-info/top_level.txt
viable-0.0.2.dist-info/RECORD
