Metadata-Version: 2.1
Name: viable
Version: 0.0.2
Summary: Diagnose source data for sound recognition ML
Home-page: https://github.com/otosense/viable
Author: OtoSense
License: apache-2.0
Platform: any
